<?xml version="1.0" encoding="windows-1252" ?>
<!DOCTYPE ViewObject SYSTEM "jbo_03_01.dtd">
<!---->
<ViewObject
  xmlns="http://xmlns.oracle.com/bc4j"
  Name="Appr_Group_Name_ROVO"
  Version="11.1.1.66.73"
  InheritPersonalization="merge"
  BindingStyle="OracleName"
  CustomQuery="true"
  PageIterMode="Full"
  UseGlueCode="false">
  <DesignTime>
    <Attr Name="_isExpertMode" Value="true"/>
  </DesignTime>
  <Properties>
    <SchemaBasedProperties>
      <LABEL
        ResId="fusion.apr.model.ROVO.Appr_Group_Name_ROVO_LABEL"/>
    </SchemaBasedProperties>
  </Properties>
  <SQLQuery>
    <![CDATA[SELECT ATTR_GRP_ID, ATTR_GRP_NAME FROM XXFND_APPR_ATTR_GROUP]]>
  </SQLQuery>
  <ViewAttribute
    Name="AttrGrpId"
    IsUpdateable="false"
    IsPersistent="false"
    IsNotNull="true"
    PrecisionRule="true"
    Type="oracle.jbo.domain.Number"
    ColumnType="NUMBER"
    AliasName="ATTR_GRP_ID"
    Expression="ATTR_GRP_ID"
    SQLType="NUMERIC">
    <DesignTime>
      <Attr Name="_DisplaySize" Value="39"/>
    </DesignTime>
  </ViewAttribute>
  <ViewAttribute
    Name="AttrGrpName"
    IsUpdateable="false"
    IsPersistent="false"
    IsNotNull="true"
    PrecisionRule="true"
    Precision="30"
    Type="java.lang.String"
    ColumnType="VARCHAR2"
    AliasName="ATTR_GRP_NAME"
    Expression="ATTR_GRP_NAME"
    SQLType="VARCHAR">
    <DesignTime>
      <Attr Name="_DisplaySize" Value="30"/>
    </DesignTime>
  </ViewAttribute>
  <ResourceBundle>
    <PropertiesBundle
      PropertiesFile="model.FunctionApprovalsModelBundle"/>
  </ResourceBundle>
</ViewObject>
